reclass/__init__.py
reclass/cli.py
reclass/config.py
reclass/constants.py
reclass/core.py
reclass/defaults.py
reclass/errors.py
reclass/settings.py
reclass/version.py
reclass/adapters/__init__.py
reclass/adapters/ansible.py
reclass/adapters/salt.py
reclass/datatypes/__init__.py
reclass/datatypes/applications.py
reclass/datatypes/classes.py
reclass/datatypes/entity.py
reclass/datatypes/exports.py
reclass/datatypes/parameters.py
reclass/output/__init__.py
reclass/output/json_outputter.py
reclass/output/yaml_outputter.py
reclass/storage/__init__.py
reclass/storage/common.py
reclass/storage/loader.py
reclass/storage/memcache_proxy.py
reclass/storage/yamldata.py
reclass/storage/mixed/__init__.py
reclass/storage/yaml_fs/__init__.py
reclass/storage/yaml_fs/directory.py
reclass/storage/yaml_git/__init__.py
reclass/utils/__init__.py
reclass/utils/dictpath.py
reclass/utils/parameterdict.py
reclass/utils/parameterlist.py
reclass/values/__init__.py
reclass/values/compitem.py
reclass/values/dictitem.py
reclass/values/invitem.py
reclass/values/item.py
reclass/values/listitem.py
reclass/values/parser.py
reclass/values/parser_funcs.py
reclass/values/refitem.py
reclass/values/scaitem.py
reclass/values/value.py
reclass/values/valuelist.py
kapicorp_reclass-2.0.0.dist-info/LICENSE
kapicorp_reclass-2.0.0.dist-info/METADATA
kapicorp_reclass-2.0.0.dist-info/WHEEL
kapicorp_reclass-2.0.0.dist-info/entry_points.txt
kapicorp_reclass-2.0.0.dist-info/top_level.txt
kapicorp_reclass-2.0.0.dist-info/RECORD
